Metadata-Version: 2.1
Name: b-d
Version: 0.4
Summary: Gaussian distributions
Home-page: UNKNOWN
Author: abcs
Author-email: sabcdefggg@gmail.com
License: UNKNOWN
Platform: UNKNOWN
